LICENSE
MANIFEST.in
README.rst
setup.cfg
setup.py
versioneer.py
artellapipe/__init__.py
artellapipe/tools/__init__.py
artellapipe/tools/dependenciesmanager/__init__.py
artellapipe/tools/dependenciesmanager/__logging__.ini
artellapipe/tools/dependenciesmanager/__version__.py
artellapipe/tools/dependenciesmanager/_version.py
artellapipe/tools/dependenciesmanager/core/__init__.py
artellapipe/tools/dependenciesmanager/core/dependenciesmanager.py
artellapipe/tools/dependenciesmanager/resources/images/dependenciesmanager_logo.png
artellapipe/tools/dependenciesmanager/widgets/__init__.py
artellapipe/tools/dependenciesmanager/widgets/dependenciesmanager.py
artellapipe_tools_dependenciesmanager.egg-info/PKG-INFO
artellapipe_tools_dependenciesmanager.egg-info/SOURCES.txt
artellapipe_tools_dependenciesmanager.egg-info/dependency_links.txt
artellapipe_tools_dependenciesmanager.egg-info/not-zip-safe
artellapipe_tools_dependenciesmanager.egg-info/requires.txt
artellapipe_tools_dependenciesmanager.egg-info/top_level.txt
tests/__init__.py
tests/test_general.py