Metadata-Version: 2.1
Name: artellapipe-tools-dependenciesmanager
Version: 0.0.5
Summary: Tool to easily manage to dependencies of DCC files
Home-page: https://github.com/ArtellaPipe/artellapipe-tools-dependenciesmanager
Author: Tomas Poveda
Author-email: tpovedatd@gmail.com
License: MIT
Platform: UNKNOWN
Provides-Extra: dev
Provides-Extra: test
